architect/__init__.py
architect/compat.py
architect/exceptions.py
architect/version.py
architect/commands/__init__.py
architect/commands/partition.py
architect/databases/__init__.py
architect/databases/bases.py
architect/databases/utilities.py
architect/databases/mysql/__init__.py
architect/databases/mysql/partition.py
architect/databases/postgresql/__init__.py
architect/databases/postgresql/partition.py
architect/databases/sqlite/__init__.py
architect/databases/sqlite/partition.py
architect/orms/__init__.py
architect/orms/bases.py
architect/orms/decorators.py
architect/orms/registry.py
architect/orms/django/__init__.py
architect/orms/django/features.py
architect/orms/peewee/__init__.py
architect/orms/peewee/features.py
architect/orms/pony/__init__.py
architect/orms/pony/features.py
architect/orms/sqlalchemy/__init__.py
architect/orms/sqlalchemy/features.py
architect/orms/sqlobject/__init__.py
architect/orms/sqlobject/features.py
architect-0.6.0.dist-info/LICENSE
architect-0.6.0.dist-info/METADATA
architect-0.6.0.dist-info/NOTICE
architect-0.6.0.dist-info/WHEEL
architect-0.6.0.dist-info/entry_points.txt
architect-0.6.0.dist-info/top_level.txt
architect-0.6.0.dist-info/RECORD
