Metadata-Version: 2.1
Name: architect
Version: 0.6.0
Summary: A set of tools which enhances ORMs written in Python with more features
Home-page: https://github.com/maxtepkeev/architect
Author: Max Tepkeev
Author-email: tepkeev@gmail.com
License: Apache 2.0
Keywords: architect,django,pony,peewee,sqlalchemy,sqlobject,partition,partitioning,database,table
Platform: UNKNOWN
Classifier: Development Status :: 3 - Alpha
Classifier: License :: OSI Approved :: Apache Software License
Classifier: Topic :: Software Development :: Libraries :: Python Modules
Classifier: Topic :: Database
Classifier: Topic :: Utilities
Classifier: Intended Audience :: Developers
Classifier: Environment :: Console
Classifier: Environment :: Web Environment
Classifier: Operating System :: OS Independent
Classifier: Programming Language :: SQL
Classifier: Programming Language :: Python :: 2.7
Classifier: Programming Language :: Python :: 3.5
Classifier: Programming Language :: Python :: 3.6
Classifier: Programming Language :: Python :: 3.7
Classifier: Programming Language :: Python :: 3.8
Classifier: Programming Language :: Python :: Implementation :: CPython
Requires-Python: >=2.7, !=3.0.*, !=3.1.*, !=3.2.*, !=3.3.*, !=3.4.*
